ZODB/ActivityMonitor.py
ZODB/BaseStorage.py
ZODB/ConflictResolution.py
ZODB/ConflictResolution.rst
ZODB/Connection.py
ZODB/DB.py
ZODB/DemoStorage.py
ZODB/DemoStorage.test
ZODB/ExportImport.py
ZODB/MappingStorage.py
ZODB/POSException.py
ZODB/UndoLogCompatible.py
ZODB/__init__.py
ZODB/_compat.py
ZODB/blob.py
ZODB/broken.py
ZODB/component.xml
ZODB/config.py
ZODB/config.xml
ZODB/conversionhack.py
ZODB/cross-database-references.rst
ZODB/event.py
ZODB/fsIndex.py
ZODB/fsrecover.py
ZODB/fstools.py
ZODB/historical_connections.rst
ZODB/interfaces.py
ZODB/loglevels.py
ZODB/mvccadapter.py
ZODB/persistentclass.py
ZODB/persistentclass.rst
ZODB/serialize.py
ZODB/storage.xml
ZODB/transact.py
ZODB/utils.py
ZODB/utils.rst
ZODB/valuedoc.py
ZODB/FileStorage/FileStorage.py
ZODB/FileStorage/__init__.py
ZODB/FileStorage/format.py
ZODB/FileStorage/fsdump.py
ZODB/FileStorage/fsoids.py
ZODB/FileStorage/fspack.py
ZODB/FileStorage/interfaces.py
ZODB/FileStorage/iterator.test
ZODB/FileStorage/tests.py
ZODB/FileStorage/zconfig.txt
ZODB/scripts/README.txt
ZODB/scripts/__init__.py
ZODB/scripts/analyze.py
ZODB/scripts/checkbtrees.py
ZODB/scripts/fsoids.py
ZODB/scripts/fsrefs.py
ZODB/scripts/fsstats.py
ZODB/scripts/fstail.py
ZODB/scripts/fstest.py
ZODB/scripts/migrate.py
ZODB/scripts/migrateblobs.py
ZODB/scripts/netspace.py
ZODB/scripts/referrers.py
ZODB/scripts/repozo.py
ZODB/scripts/space.py
ZODB/scripts/zodbload.py
ZODB/scripts/manual_tests/test-checker.fs
ZODB/scripts/manual_tests/testfstest.py
ZODB/scripts/tests/__init__.py
ZODB/scripts/tests/fstail.txt
ZODB/scripts/tests/referrers.txt
ZODB/scripts/tests/test_doc.py
ZODB/scripts/tests/test_fsdump_fsstats.py
ZODB/scripts/tests/test_fstest.py
ZODB/scripts/tests/test_repozo.py
ZODB/tests/BasicStorage.py
ZODB/tests/ConflictResolution.py
ZODB/tests/Corruption.py
ZODB/tests/HistoryStorage.py
ZODB/tests/IExternalGC.test
ZODB/tests/IteratorStorage.py
ZODB/tests/MTStorage.py
ZODB/tests/MVCCMappingStorage.py
ZODB/tests/MinPO.py
ZODB-6.0.dist-info/COPYING
ZODB-6.0.dist-info/LICENSE.txt
ZODB-6.0.dist-info/METADATA
ZODB-6.0.dist-info/WHEEL
ZODB-6.0.dist-info/entry_points.txt
ZODB-6.0.dist-info/top_level.txt
ZODB-6.0.dist-info/RECORD
