Metadata-Version: 2.1
Name: ZODB
Version: 6.0
Summary: ZODB, a Python object-oriented database
Home-page: http://zodb-docs.readthedocs.io
Author: Jim Fulton
Author-email: jim@zope.com
Maintainer: Zope Foundation and Contributors
Maintainer-email: zodb-dev@zope.dev
License: ZPL 2.1
Keywords: database nosql python zope
Platform: any
Classifier: Intended Audience :: Developers
Classifier: License :: OSI Approved :: Zope Public License
Classifier: Programming Language :: Python
Classifier: Programming Language :: Python :: 3
Classifier: Programming Language :: Python :: 3.7
Classifier: Programming Language :: Python :: 3.8
Classifier: Programming Language :: Python :: 3.9
Classifier: Programming Language :: Python :: 3.10
Classifier: Programming Language :: Python :: 3.11
Classifier: Programming Language :: Python :: 3.12
Classifier: Programming Language :: Python :: Implementation :: CPython
Classifier: Programming Language :: Python :: Implementation :: PyPy
Classifier: Topic :: Database
Classifier: Topic :: Software Development :: Libraries :: Python Modules
Classifier: Operating System :: Microsoft :: Windows
Classifier: Operating System :: Unix
Classifier: Framework :: ZODB
Requires-Python: >=3.7
License-File: LICENSE.txt
License-File: COPYING
Requires-Dist: persistent>=4.4.0
Requires-Dist: BTrees>=4.2.0
Requires-Dist: ZConfig
Requires-Dist: transaction>=2.4
Requires-Dist: zc.lockfile
Requires-Dist: zope.interface
Requires-Dist: zodbpickle>=1.0.1
Provides-Extra: test
Requires-Dist: manuel; extra == "test"
Requires-Dist: zope.testing; extra == "test"
Requires-Dist: zope.testrunner>=4.4.6; extra == "test"
Provides-Extra: docs
Requires-Dist: Sphinx<7; extra == "docs"
Requires-Dist: ZODB; extra == "docs"
Requires-Dist: j1m.sphinxautozconfig; extra == "docs"
Requires-Dist: sphinx_rtd_theme; extra == "docs"
Requires-Dist: sphinxcontrib_zopeext; extra == "docs"
